pryvx/__init__.py
pryvx/fl_client.py
pryvx/fl_ensemble.py
pryvx/fl_server.py
pryvx/gdp.py
pryvx/ldp.py
pryvx/phe.py
pryvx/pryvx_pb2.py
pryvx/pryvx_pb2_grpc.py
pryvx/psi.py
pryvx/rtphe.py
pryvx/smpc.py
pryvx-2.6.0.dist-info/LICENSE
pryvx-2.6.0.dist-info/METADATA
pryvx-2.6.0.dist-info/WHEEL
pryvx-2.6.0.dist-info/top_level.txt
pryvx-2.6.0.dist-info/RECORD
