Metadata-Version: 2.1
Name: pryvx
Version: 2.6.0
Summary: A comprehensive package for privacy-enhancing technologies
Home-page: UNKNOWN
Author: PryvX (Jayesh Kenaudekar)
Author-email: <jayesh@pryvx.com>
License: MIT
Keywords: python,privacy-preserving,federated-learning,machine-learning,privacy-enhancing-technology,smpc,private-set-intersection
Platform: UNKNOWN
Classifier: Programming Language :: Python :: 3.9
Classifier: Intended Audience :: Developers
Classifier: License :: OSI Approved :: MIT License
Classifier: Operating System :: OS Independent
License-File: LICENSE
Requires-Dist: grpcio
Requires-Dist: grpcio-tools
Requires-Dist: protobuf
Requires-Dist: sympy
Requires-Dist: numpy
Requires-Dist: scikit-learn
